projective_simulation/__init__.py
projective_simulation/_modidx.py
projective_simulation/contributing_guide.py
projective_simulation/ECMs/__init__.py
projective_simulation/ECMs/core.py
projective_simulation/ECMs/priming.py
projective_simulation/agents/__init__.py
projective_simulation/agents/core.py
projective_simulation/agents/foraging.py
projective_simulation/envs/__init__.py
projective_simulation/envs/core.py
projective_simulation/envs/foraging.py
projective_simulation/methods/__init__.py
projective_simulation/methods/lib_helpers.py
projective_simulation/methods/preprocessors.py
projective_simulation/methods/transforms.py
projective_simulation-0.0.2.dist-info/LICENSE
projective_simulation-0.0.2.dist-info/METADATA
projective_simulation-0.0.2.dist-info/WHEEL
projective_simulation-0.0.2.dist-info/entry_points.txt
projective_simulation-0.0.2.dist-info/top_level.txt
projective_simulation-0.0.2.dist-info/RECORD
