Metadata-Version: 2.1
Name: projective_simulation
Version: 0.0.2
Summary: Library for Projective Simulation
Home-page: https://github.com/{user}/projective_simulation/
Author: QIC-UIBK
Author-email: gorka.munoz-gil@uibk.ac.at
License: Apache Software License 2.0
Keywords: RL,ML
Classifier: Development Status :: 3 - Alpha
Classifier: Intended Audience :: Developers
Classifier: Natural Language :: English
Classifier: Programming Language :: Python :: 3.10
Classifier: License :: OSI Approved :: Apache Software License
Requires-Python: >=3.10
License-File: LICENSE
Requires-Dist: nbdev
Requires-Dist: numpy
Requires-Dist: matplotlib
Requires-Dist: scipy
Provides-Extra: dev
